Metadata-Version: 2.1
Name: camera-API
Version: 1.0.7
Summary: Used to accessing the camera.
Author: Sivabalan T
Author-email: sivabalan.t@e-consystems.com
Classifier: Programming Language :: Python :: 3
